randomnwn/__init__.py
randomnwn/_models.py
randomnwn/calculations.py
randomnwn/dynamics.py
randomnwn/fromtext.py
randomnwn/line_functions.py
randomnwn/nanowire_network.py
randomnwn/nanowires.py
randomnwn/plotting.py
randomnwn/typing.py
randomnwn/units.py
randomnwn/version.py
randomnwn-0.5.6.dist-info/licenses/LICENSE
randomnwn-0.5.6.dist-info/METADATA
randomnwn-0.5.6.dist-info/WHEEL
randomnwn-0.5.6.dist-info/top_level.txt
randomnwn-0.5.6.dist-info/RECORD
