Metadata-Version: 2.4
Name: randomnwn
Version: 0.5.6
Summary: Modelling and analyzing random nanowire networks in Python.
Home-page: https://github.com/marcus-k/Random-NWNs
Author: Marcus Kasdorf
Author-email: marcus.kasdorf@ucalgary.ca
License: GNU General Public License v3
Requires-Python: >=3.10
License-File: LICENSE
Requires-Dist: matplotlib>=3.8.4
Requires-Dist: networkx>=3.1
Requires-Dist: numpy>=1.26.4
Requires-Dist: scipy>=1.13.0
Requires-Dist: Shapely<3,>=2.0.4
Dynamic: author
Dynamic: author-email
Dynamic: description
Dynamic: description-content-type
Dynamic: home-page
Dynamic: license
Dynamic: license-file
Dynamic: requires-dist
Dynamic: requires-python
Dynamic: summary
